KotlinForAndroidDevelopersZhongwenfanyi/README.md
KotlinForAndroidDevelopersZhongwenfanyi/__init__.py
KotlinForAndroidDevelopersZhongwenfanyi/__main__.py
KotlinForAndroidDevelopersZhongwenfanyi/file.epub
KotlinForAndroidDevelopersZhongwenfanyi/index.html
KotlinForAndroidDevelopersZhongwenfanyi/css/__init__.py
KotlinForAndroidDevelopersZhongwenfanyi/css/annotations.css
KotlinForAndroidDevelopersZhongwenfanyi/css/main.css
KotlinForAndroidDevelopersZhongwenfanyi/css/normalize.css
KotlinForAndroidDevelopersZhongwenfanyi/css/popup.css
KotlinForAndroidDevelopersZhongwenfanyi/font/__init__.py
KotlinForAndroidDevelopersZhongwenfanyi/font/fontello.eot
KotlinForAndroidDevelopersZhongwenfanyi/font/fontello.svg
KotlinForAndroidDevelopersZhongwenfanyi/font/fontello.ttf
KotlinForAndroidDevelopersZhongwenfanyi/font/fontello.woff
KotlinForAndroidDevelopersZhongwenfanyi/img/__init__.py
KotlinForAndroidDevelopersZhongwenfanyi/img/annotator-glyph-sprite.png
KotlinForAndroidDevelopersZhongwenfanyi/img/annotator-icon-sprite.png
KotlinForAndroidDevelopersZhongwenfanyi/img/apple-touch-icon.png
KotlinForAndroidDevelopersZhongwenfanyi/img/cancelfullscreen.png
KotlinForAndroidDevelopersZhongwenfanyi/img/close.png
KotlinForAndroidDevelopersZhongwenfanyi/img/fullscreen.png
KotlinForAndroidDevelopersZhongwenfanyi/img/loader.gif
KotlinForAndroidDevelopersZhongwenfanyi/img/menu-icon.png
KotlinForAndroidDevelopersZhongwenfanyi/img/save.png
KotlinForAndroidDevelopersZhongwenfanyi/img/saved.png
KotlinForAndroidDevelopersZhongwenfanyi/img/settings-s.png
KotlinForAndroidDevelopersZhongwenfanyi/img/settings.png
KotlinForAndroidDevelopersZhongwenfanyi/img/star.png
KotlinForAndroidDevelopersZhongwenfanyi/js/__init__.py
KotlinForAndroidDevelopersZhongwenfanyi/js/epub.js
KotlinForAndroidDevelopersZhongwenfanyi/js/epub.min.js
KotlinForAndroidDevelopersZhongwenfanyi/js/epub.min.map
KotlinForAndroidDevelopersZhongwenfanyi/js/hooks.min.js
KotlinForAndroidDevelopersZhongwenfanyi/js/hooks.min.map
kotlin_for_android_developers_zhongwenfanyi-2024.3.1.0.dist-info/METADATA
kotlin_for_android_developers_zhongwenfanyi-2024.3.1.0.dist-info/WHEEL
kotlin_for_android_developers_zhongwenfanyi-2024.3.1.0.dist-info/entry_points.txt
kotlin_for_android_developers_zhongwenfanyi-2024.3.1.0.dist-info/top_level.txt
kotlin_for_android_developers_zhongwenfanyi-2024.3.1.0.dist-info/RECORD
